[
  {
    "eventYear": 2024,
    "participantCount": 74,
    "moneyRaised": 103285
  },
  {
    "eventYear": 2023,
    "participantCount": 128,
    "moneyRaised": 132561
  },
  {
    "eventYear": 2022,
    "participantCount": 121,
    "moneyRaised": 118445
  },
  {
    "eventYear": 2019,
    "participantCount": 183,
    "moneyRaised": 100190
  },
  {
    "eventYear": 2018,
    "participantCount": 146,
    "moneyRaised": 79788
  },
  {
    "eventYear": 2017,
    "participantCount": 122,
    "moneyRaised": 62611
  },
  {
    "eventYear": 2016,
    "participantCount": 128,
    "moneyRaised": 53019
  },
  {
    "eventYear": 2015,
    "participantCount": 113,
    "moneyRaised": 36466
  },
  {
    "eventYear": 2014,
    "participantCount": 87,
    "moneyRaised": 32169
  },
  {
    "eventYear": 2013,
    "participantCount": 79,
    "moneyRaised": 14164
  },
  {
    "eventYear": 2012,
    "participantCount": 107,
    "moneyRaised": 32452
  },
  {
    "eventYear": 2011,
    "participantCount": 53,
    "moneyRaised": 21696
  }
]
