[
  {
    "name": "ESET Research Czech s.r.o.",
    "web": "https://www.eset.com/cz/",
    "image": "eset.png"
  },
  {
    "name": "Obec Albrechtice v Jizerských horách",
    "web": "https://www.albrechtice-jh.cz/",
    "image": "albrechtice.png"
  },
  {
    "name": "Obec Jiřetín pod Bukovou",
    "web": "https://www.jiretinpb.cz",
    "image": "jiretin-pod-bukovou.png"
  },
  {
    "name": "Obec Josefův Důl",
    "web": "https://josefuvdul.eu",
    "image": "josefuv-dul.png"
  },
  {
    "name": "Tesařství Petr Smutný",
    "web": "https://www.smutny-tesarstvi.cz/",
    "image": "smutny.png"
  },
  {
    "name": "Kitl s.r.o.",
    "web": "https://kitl.cz/",
    "image": "kitl.png"
  },
  {
    "name": "VESPO s.r.o.",
    "web": "https://www.vespo.cz/",
    "image": "vespo.jpg"
  },
  {
    "name": "MUDr. Karel Stuchlík",
    "web": "#",
    "image": "sponsor.png"
  },
  {
    "name": "Aleš Zeman – Zemní práce",
    "web": "#",
    "image": "aleszeman.png"
  },
  {
    "name": "Živé firmy (DATABOX s.r.o.)",
    "web": "https://www.zivefirmy.cz",
    "image": "zivefirmy.png"
  },
  {
    "name": "JAVECAR Jaroslav Veverka",
    "web": "#",
    "image": "javecar.png"
  },
  {
    "name": "Stavební práce Sucharda",
    "web": "https://www.fasuchardaivan.cz",
    "image": "sucharda.png"
  },
  {
    "name": "Firma Mitlík s.r.o.",
    "web": "#",
    "image": "mitlik.png"
  },
  {
    "name": "Senátor Jaroslav Zeman",
    "web": "#",
    "image": "zeman.png"
  },
  {
    "name": "Kominictví Jan Pipek",
    "web": "https://zelinkapipek.sluzby.cz/",
    "image": "sponsor.png"
  },
  {
    "name": "Penzion Jana Hübnerová",
    "web": "https://www.penzionhubnerova.cz/",
    "image": "sponsor.png"
  },
  {
    "name": "Penzion Tipos",
    "web": "#",
    "image": "sponsor.png"
  },
  {
    "name": "Malířství Holý",
    "web": "#",
    "image": "sponsor.png"
  },
  {
    "name": "Penzion Max",
    "web": "#",
    "image": "sponsor.png"
  },
  {
    "name": "Cukrárna u Voborníků",
    "web": "https://www.pensiontereza.cz",
    "image": "sponsor.png"
  },
  {
    "name": "Penzion Světlý vrch - manželé Huškovi",
    "web": "#",
    "image": "sponsor.png"
  },
  {
    "name": "Bohuslav Pavelek, stavební práce",
    "web": "#",
    "image": "sponsor.png"
  },
  {
    "name": "FEEL s.r.o. Tomáš Feix",
    "web": "#",
    "image": "sponsor.png"
  },
  {
    "name": "StepaZem s.r.o. Petr Štěpánek",
    "web": "#",
    "image": "sponsor.png"
  },
  {
    "name": "TEMBO BRAND s.r.o. Petr Urban",
    "web": "#",
    "image": "sponsor.png"
  },
  {
    "name": "Truhlářství Miroslav Jelínek",
    "web": "#",
    "image": "sponsor.png"
  },
  {
    "name": "Hospůdka u silnice",
    "web": "#",
    "image": "sponsor.png"
  }
]
